poetry_tutorial_project/__init__.py
poetry_tutorial_project/alarm_panel_callback.py
poetry_tutorial_project/alarm_panel_layout.py
poetry_tutorial_project/static/social.jpg
poetry_tutorial_project/util/size.py
demo_project_ding-0.1.1.dist-info/LICENSE
demo_project_ding-0.1.1.dist-info/WHEEL
demo_project_ding-0.1.1.dist-info/METADATA
demo_project_ding-0.1.1.dist-info/RECORD
