Metadata-Version: 2.1
Name: demo-project-ding
Version: 0.1.1
Summary: 
Author: shengqin ding
Author-email: dshengq@163.com
Requires-Python: >=3.8,<4.0
Classifier: Programming Language :: Python :: 3
Classifier: Programming Language :: Python :: 3.8
Classifier: Programming Language :: Python :: 3.9
Classifier: Programming Language :: Python :: 3.10
